mmaputils/__init__.py
mmaputils/mmapcursor.py
mmaputils-0.1.0.dist-info/LICENSE
mmaputils-0.1.0.dist-info/METADATA
mmaputils-0.1.0.dist-info/WHEEL
mmaputils-0.1.0.dist-info/top_level.txt
mmaputils-0.1.0.dist-info/RECORD
