Metadata-Version: 2.1
Name: mmaputils
Version: 0.1.0
Summary: Various utilities wrapping the stdlib mmap module.
Home-page: https://github.com/a-bison/mmaputils
Author: a-bison
Author-email: aliteralbison@protonmail.com
Classifier: Operating System :: Microsoft :: Windows
Classifier: Operating System :: POSIX :: Linux
Classifier: Intended Audience :: Developers
Classifier: Topic :: Utilities
Requires-Python: >=3.6
License-File: LICENSE
